spacesense/__init__.py
spacesense/__version__.py
spacesense/config.py
spacesense/core.py
spacesense/file_handler.py
spacesense/geoutils.py
spacesense/grpc_auth.py
spacesense/grpc_client.py
spacesense/job.py
spacesense/ml_utils.py
spacesense/utils.py
spacesense/collections/__init__.py
spacesense/collections/models.py
spacesense/common/proto/backend/backend_pb2.py
spacesense/common/proto/backend/backend_pb2_grpc.py
spacesense/resources/config.json
spacesense/resources/server.crt
spacesense-0.9.0.dist-info/LICENSE
spacesense-0.9.0.dist-info/METADATA
spacesense-0.9.0.dist-info/WHEEL
spacesense-0.9.0.dist-info/top_level.txt
spacesense-0.9.0.dist-info/RECORD
