Metadata-Version: 2.1
Name: spacesense
Version: 0.9.0
Summary: Spacesense Client Library
Home-page: https://spacesense.gitlab.io/client-library
Author: SpaceSense
Author-email: support@spacesense.ai
License: Apache 2.0
Platform: UNKNOWN
Classifier: Programming Language :: Python :: 3
Classifier: Operating System :: OS Independent
Requires-Python: >=3.6
License-File: LICENSE
Requires-Dist: geopandas (>=0.10.2)
Requires-Dist: grpcio (>=1.42.0)
Requires-Dist: grpcio-tools (>=1.42.0)
Requires-Dist: importlib-metadata (<5.0)
Requires-Dist: matplotlib (>=3.3.3)
Requires-Dist: netCDF4 (>=1.5.8)
Requires-Dist: protobuf (==3.20.3)
Requires-Dist: pyjwt[crypto] (>=2.3.0)
Requires-Dist: rasterio (>=1.1.8)
Requires-Dist: rioxarray (>=0.9.1)
Requires-Dist: sat-stac (>=0.4.1)
Requires-Dist: scikit-image (>=0.18.2)
Requires-Dist: scikit-learn (>1.0)
Requires-Dist: tqdm (>=4.64.1)
Requires-Dist: xarray (>=0.19.0)
Provides-Extra: dev
Requires-Dist: commitizen (==2.21.2) ; extra == 'dev'
Requires-Dist: coverage (==5.3) ; extra == 'dev'
Requires-Dist: google-auth (==2.13.0) ; extra == 'dev'
Requires-Dist: grpc-interceptor (==0.13.1) ; extra == 'dev'
Requires-Dist: grpcio-tools (==1.42.0) ; extra == 'dev'
Requires-Dist: pre-commit (==2.17.0) ; extra == 'dev'
Requires-Dist: pytest (==7.1.2) ; extra == 'dev'
Requires-Dist: pytest-cov (==2.10.1) ; extra == 'dev'
Requires-Dist: pytest-xdist (==2.5.0) ; extra == 'dev'
Requires-Dist: twine (==3.8.0) ; extra == 'dev'
Requires-Dist: wheel (==0.37.1) ; extra == 'dev'
Provides-Extra: doc
Requires-Dist: apidocs (==0.1.0) ; extra == 'doc'
Requires-Dist: Django (==3.2.15) ; extra == 'doc'
Requires-Dist: docutils (==0.17.1) ; extra == 'doc'
Requires-Dist: MarkupSafe (==2.1.1) ; extra == 'doc'
Requires-Dist: myst-parser (==0.18.0) ; extra == 'doc'
Requires-Dist: nbsphinx (==0.9.1) ; extra == 'doc'
Requires-Dist: pandoc (==2.2) ; extra == 'doc'
Requires-Dist: Sphinx (==4.5.0) ; extra == 'doc'
Requires-Dist: sphinx-book-theme (==0.3.3) ; extra == 'doc'
Requires-Dist: sphinx-copybutton (==0.5.0) ; extra == 'doc'
Requires-Dist: sphinx-gallery (==0.11.1) ; extra == 'doc'
Requires-Dist: sphinx-rtd-theme (==1.0.0) ; extra == 'doc'
Requires-Dist: sphinx-autodoc-defaultargs (==0.1.2) ; extra == 'doc'
Requires-Dist: tensorflow (==2.6) ; extra == 'doc'
Requires-Dist: tqdm (==4.64.1) ; extra == 'doc'
Provides-Extra: ml
Requires-Dist: tensorflow (>=2.6) ; extra == 'ml'
